gitool/__init__.py
gitool/__main__.py
gitool/arguments.py
gitool/config.py
gitool/exception.py
gitool/gitool.py
gitool/logging.py
gitool/methods.py
gitool/repository.py
gitool/util.py
gitool/version.py
gitool-1.2.1.dist-info/LICENSE
gitool-1.2.1.dist-info/METADATA
gitool-1.2.1.dist-info/WHEEL
gitool-1.2.1.dist-info/entry_points.txt
gitool-1.2.1.dist-info/top_level.txt
gitool-1.2.1.dist-info/RECORD
