Metadata-Version: 2.1
Name: gitool
Version: 1.2.1
Summary: A tool for managing git repositories.
Home-page: https://pypi.python.org/pypi/gitool
Author: eikendev
Author-email: raphael@eiken.dev
License: MIT
Keywords: git,repository,manager,cli
Platform: UNKNOWN
Classifier: Development Status :: 4 - Beta
Classifier: Intended Audience :: Developers
Classifier: License :: OSI Approved :: MIT License
Classifier: Programming Language :: Python :: 3
Classifier: Topic :: Utilities
Classifier: Environment :: Console
Classifier: Operating System :: POSIX
Requires-Python: >=3
Requires-Dist: colorama ; python_version >= "0.3.9"
Requires-Dist: GitPython ; python_version >= "2.1.8"
